customlib/__init__.py
customlib/s3upload.py
customlibsdk-0.0.2.dist-info/licenses/LICENSE
customlibsdk-0.0.2.dist-info/METADATA
customlibsdk-0.0.2.dist-info/WHEEL
customlibsdk-0.0.2.dist-info/top_level.txt
customlibsdk-0.0.2.dist-info/RECORD
