Metadata-Version: 2.4
Name: customlibSDK
Version: 0.0.2
Summary: Library to upload mobile insurance document to s3 bucket
Author: Gaurv Kumar
Maintainer: Gaurav Kumar
License-File: LICENSE
Requires-Dist: boto3
Dynamic: author
Dynamic: license-file
Dynamic: maintainer
Dynamic: requires-dist
Dynamic: summary
